Metadata-Version: 2.1
Name: schedular
Version: 1.0.4
Summary: Schedular is here to schedule jobs by cut off time or jobs that require start+end+interval.
Home-page: https://github.com/noxqs/schedular
Author: Morgan NoXQS Heijdemann
Author-email: targhan@gmail.com
License: MIT License
Platform: UNKNOWN
Classifier: Programming Language :: Python :: 2
Classifier: License :: OSI Approved :: MIT License
Classifier: Operating System :: OS Independent
